paravalid/__init__.py
paravalid/cli.py
paravalid/core.py
paravalid/json_parallel.py
paravalid/pydantic_parallel.py
paravalid-0.1.0.dist-info/WHEEL
paravalid-0.1.0.dist-info/entry_points.txt
paravalid-0.1.0.dist-info/METADATA
paravalid-0.1.0.dist-info/RECORD
