Metadata-Version: 2.3
Name: paravalid
Version: 0.1.0
Summary: Parallel validation and serialization for Python 3.13+
Author: yoon-yoo-sang
Author-email: yoon-yoo-sang <yyss6188@naver.com>
Requires-Dist: pydantic>=2.0.0 ; extra == 'pydantic'
Requires-Python: >=3.13
Provides-Extra: pydantic
